picsellia_elasticsearch_client/__init__.py
picsellia_elasticsearch_client/abstract_client.py
picsellia_elasticsearch_client/alert.py
picsellia_elasticsearch_client/client.py
picsellia_elasticsearch_client/document.py
picsellia_elasticsearch_client/error.py
picsellia_elasticsearch_client/metric.py
picsellia_elasticsearch_client/mocked_client.py
picsellia_elasticsearch_client-1.1.0.dist-info/LICENSE
picsellia_elasticsearch_client-1.1.0.dist-info/WHEEL
picsellia_elasticsearch_client-1.1.0.dist-info/METADATA
picsellia_elasticsearch_client-1.1.0.dist-info/RECORD
