Metadata-Version: 2.1
Name: picsellia-elasticsearch-client
Version: 1.1.0
Summary: Package wrapping elasticsearch client for Picsellia
License: MSI
Author: Thomas Darget
Author-email: thomas.darget@picsellia.com
Requires-Python: >=3.8,<4.0
Classifier: License :: Other/Proprietary License
Classifier: Programming Language :: Python :: 3
Classifier: Programming Language :: Python :: 3.8
Classifier: Programming Language :: Python :: 3.9
Classifier: Programming Language :: Python :: 3.10
Requires-Dist: ElasticMock (>=1.8.1,<2.0.0)
Requires-Dist: elasticsearch (==7.16.2)
